MQdk/__init__.py
MQdk/main.py
MQdk-0.0.4.dist-info/METADATA
MQdk-0.0.4.dist-info/WHEEL
MQdk-0.0.4.dist-info/top_level.txt
MQdk-0.0.4.dist-info/RECORD
