Metadata-Version: 2.1
Name: MQdk
Version: 0.0.4
